springburn/__init__.py
springburn/common.py
springburn/springburn.py
springburn-0.0.1.dist-info/LICENSE
springburn-0.0.1.dist-info/METADATA
springburn-0.0.1.dist-info/WHEEL
springburn-0.0.1.dist-info/entry_points.txt
springburn-0.0.1.dist-info/top_level.txt
springburn-0.0.1.dist-info/RECORD
